django_kelove_admin_lte/__init__.py
django_kelove_admin_lte/apps.py
django_kelove_admin_lte/conf.py
django_kelove_admin_lte/static/kelove_admin_lte/dist/css/adminlte.css
django_kelove_admin_lte/static/kelove_admin_lte/dist/css/adminlte.css.map
django_kelove_admin_lte/static/kelove_admin_lte/dist/css/adminlte.min.css
django_kelove_admin_lte/static/kelove_admin_lte/dist/css/adminlte.min.css.map
django_kelove_admin_lte/static/kelove_admin_lte/dist/css/alt/adminlte.components.css
django_kelove_admin_lte/static/kelove_admin_lte/dist/css/alt/adminlte.components.css.map
django_kelove_admin_lte/static/kelove_admin_lte/dist/css/alt/adminlte.components.min.css
django_kelove_admin_lte/static/kelove_admin_lte/dist/css/alt/adminlte.components.min.css.map
django_kelove_admin_lte/static/kelove_admin_lte/dist/css/alt/adminlte.core.css
django_kelove_admin_lte/static/kelove_admin_lte/dist/css/alt/adminlte.core.css.map
django_kelove_admin_lte/static/kelove_admin_lte/dist/css/alt/adminlte.core.min.css
django_kelove_admin_lte/static/kelove_admin_lte/dist/css/alt/adminlte.core.min.css.map
django_kelove_admin_lte/static/kelove_admin_lte/dist/css/alt/adminlte.extra-components.css
django_kelove_admin_lte/static/kelove_admin_lte/dist/css/alt/adminlte.extra-components.css.map
django_kelove_admin_lte/static/kelove_admin_lte/dist/css/alt/adminlte.extra-components.min.css
django_kelove_admin_lte/static/kelove_admin_lte/dist/css/alt/adminlte.extra-components.min.css.map
django_kelove_admin_lte/static/kelove_admin_lte/dist/css/alt/adminlte.pages.css
django_kelove_admin_lte/static/kelove_admin_lte/dist/css/alt/adminlte.pages.css.map
django_kelove_admin_lte/static/kelove_admin_lte/dist/css/alt/adminlte.pages.min.css
django_kelove_admin_lte/static/kelove_admin_lte/dist/css/alt/adminlte.pages.min.css.map
django_kelove_admin_lte/static/kelove_admin_lte/dist/css/alt/adminlte.plugins.css
django_kelove_admin_lte/static/kelove_admin_lte/dist/css/alt/adminlte.plugins.css.map
django_kelove_admin_lte-0.1.4.dist-info/WHEEL
django_kelove_admin_lte-0.1.4.dist-info/METADATA
django_kelove_admin_lte-0.1.4.dist-info/RECORD
