Metadata-Version: 2.1
Name: django-kelove-admin-lte
Version: 0.1.4
Summary: AdminLTE Template for Django Admin
Home-page: https://xqitw.coding.net/public/django-kelove-admin-lte/django-kelove-admin-lte/git
License: Apache-2.0
Keywords: template,django,django-admin,django-kelove-admin,django-kelove-admin-lte,AdminLTE
Author: IT小强xqitw.cn
Author-email: mail@xqitw.cn
Maintainer: IT小强xqitw.cn
Maintainer-email: mail@xqitw.cn
Requires-Python: >=3.6,<4.0
Classifier: Development Status :: 3 - Alpha
Classifier: Framework :: Django :: 3.1
Classifier: Intended Audience :: Developers
Classifier: License :: OSI Approved :: Apache Software License
Classifier: Natural Language :: Chinese (Simplified)
Classifier: Programming Language :: Python :: 3
Classifier: Programming Language :: Python :: 3.6
Classifier: Programming Language :: Python :: 3.7
Classifier: Programming Language :: Python :: 3.8
Classifier: Programming Language :: Python :: 3.9
Requires-Dist: django (>=3.1,<4.0)
Project-URL: Documentation, https://xqitw.coding.net/public/django-kelove-admin-lte/django-kelove-admin-lte/git
Project-URL: Repository, https://e.coding.net/xqitw/django-kelove-admin-lte/django-kelove-admin-lte.git
